pytong/__init__.py
pytong/base.py
pytong/config.py
pytong/log.py
pytong/log2.py
pytong/py.typed
pytong-0.2.2.dist-info/LICENSE
pytong-0.2.2.dist-info/METADATA
pytong-0.2.2.dist-info/WHEEL
pytong-0.2.2.dist-info/top_level.txt
pytong-0.2.2.dist-info/RECORD
