Metadata-Version: 2.1
Name: pytong
Version: 0.2.2
Summary: Rich Tong's Fine Utilities
Home-page: https://github.com/richtong/pytong
Author: Richard Tong
Author-email: rich@tongfamily.com
License: UNKNOWN
Project-URL: Bug Tracker, https://github.com/richtong/pytong/issues
Platform: UNKNOWN
Classifier: Programming Language :: Python :: 3
Classifier: Programming Language :: Python :: 3.8
Classifier: Programming Language :: Python :: 3.9
Classifier: Programming Language :: Python :: 3.10
Classifier: License :: OSI Approved :: MIT License
Classifier: Operating System :: OS Independent
Requires-Python: >=3.8
License-File: LICENSE
